pqutils/PQDatabase.py
pqutils/PQLogger.py
pqutils/PQThread.py
pqutils/__init__.py
pqutils-1.0.9.dist-info/METADATA
pqutils-1.0.9.dist-info/WHEEL
pqutils-1.0.9.dist-info/top_level.txt
pqutils-1.0.9.dist-info/RECORD
